pairlist.py
cpairlist.cpython-311-darwin.so
pairlist-0.6.3.dist-info/METADATA
pairlist-0.6.3.dist-info/WHEEL
pairlist-0.6.3.dist-info/RECORD
