Metadata-Version: 2.4
Name: pairlist
Version: 0.6.3
Summary: Generate neighbor list for the particles in a periodic boundary cell.
License: MIT
Author: vitroid
Author-email: vitroid@gmail.com
Requires-Python: >=3.9,<4.0
Classifier: License :: OSI Approved :: MIT License
Classifier: Programming Language :: Python :: 3
Classifier: Programming Language :: Python :: 3.9
Classifier: Programming Language :: Python :: 3.10
Classifier: Programming Language :: Python :: 3.11
Classifier: Programming Language :: Python :: 3.12
Classifier: Programming Language :: Python :: 3.13
Classifier: Programming Language :: Python :: 3.14
Requires-Dist: numpy (>=2.0,<3.0)
